tests/__init__.py
tests/test_db_purge.py
django_db_purge-0.2.dist-info/LICENSE
django_db_purge-0.2.dist-info/METADATA
django_db_purge-0.2.dist-info/WHEEL
django_db_purge-0.2.dist-info/top_level.txt
django_db_purge-0.2.dist-info/RECORD
